README.rst
setup.py
azure/cli/command_modules/webapp/__init__.py
azure/cli/command_modules/webapp/_help.py
azure/cli/command_modules/webapp/_params.py
azure/cli/command_modules/webapp/custom.py
azure/cli/command_modules/webapp/generated.py
azure_cli_webapp.egg-info/PKG-INFO
azure_cli_webapp.egg-info/SOURCES.txt
azure_cli_webapp.egg-info/dependency_links.txt
azure_cli_webapp.egg-info/namespace_packages.txt
azure_cli_webapp.egg-info/requires.txt
azure_cli_webapp.egg-info/top_level.txt